filter_crop/__init__.py
filter_crop/filter.py
filter_crop-0.1.13.dist-info/licenses/LICENSE
filter_crop-0.1.13.dist-info/METADATA
filter_crop-0.1.13.dist-info/WHEEL
filter_crop-0.1.13.dist-info/top_level.txt
filter_crop-0.1.13.dist-info/RECORD
