Metadata-Version: 2.4
Name: filter_crop
Version: 0.1.13
License-Expression: Apache-2.0
Classifier: Programming Language :: Python :: 3
Classifier: Programming Language :: Python :: 3.10
Classifier: Programming Language :: Python :: 3.11
Classifier: Programming Language :: Python :: 3.12
Classifier: Programming Language :: Python :: 3.13
Requires-Python: <3.14,>=3.10
License-File: LICENSE
Requires-Dist: openfilter[all]==0.1.20
Provides-Extra: dev
Requires-Dist: build==1.4.0; extra == "dev"
Requires-Dist: setuptools==80.10.1; extra == "dev"
Requires-Dist: twine==6.2.0; extra == "dev"
Requires-Dist: wheel==0.46.2; extra == "dev"
Requires-Dist: pytest==9.0.2; extra == "dev"
Requires-Dist: pytest-cov==7.0.0; extra == "dev"
Dynamic: license-file
